SpacePyTraders/__init__.py
SpacePyTraders/client.py
SpacePyTraders/models.py
SpacePyTraders-0.0.5.dist-info/LICENSE.txt
SpacePyTraders-0.0.5.dist-info/METADATA
SpacePyTraders-0.0.5.dist-info/WHEEL
SpacePyTraders-0.0.5.dist-info/top_level.txt
SpacePyTraders-0.0.5.dist-info/RECORD
