Metadata-Version: 2.1
Name: SpacePyTraders
Version: 0.0.5
Summary: Access the Space Traders API with Python
Home-page: https://github.com/ZacHooper/spacePyTraders
Author: Zac Hooper
Author-email: zac.g.hooper@gmail.com
License: UNKNOWN
Platform: UNKNOWN
Classifier: Programming Language :: Python :: 3
Classifier: Programming Language :: Python :: 3.6
Classifier: Programming Language :: Python :: 3.7
Classifier: Programming Language :: Python :: 3.8
Classifier: License :: OSI Approved :: GNU General Public License v2 or later (GPLv2+)
Classifier: Operating System :: OS Independent
Requires-Dist: requests (~=2.25.1)
